MANIFEST.in
README.md
README.txt
requirements.txt
setup.cfg
setup.py
Staxing.egg-info/PKG-INFO
Staxing.egg-info/SOURCES.txt
Staxing.egg-info/dependency_links.txt
Staxing.egg-info/requires.txt
Staxing.egg-info/top_level.txt
staxing/__init__.py
staxing/actions.py
staxing/assignment.py
staxing/helper.py
staxing/page_load.py
tests/__init__.py
tests/test_staxing_actions.py
tests/test_staxing_assignment.py
tests/test_staxing_helper.py
tests/test_staxing_page_load.py