Metadata-Version: 1.0
Name: Staxing
Version: 0.0.58
Summary: Stax test base
Home-page: https://github.com/openstax/staxing
Author: OpenStax QA
Author-email: greg@openstax.org
License: Creative Commons Attribution 4.0 International Public License
Platform: UNKNOWN
